CONTRIBUTORS.txt
MANIFEST.in
README.txt
setup.cfg
setup.py
Products/__init__.py
Products.SimpleReference.egg-info/PKG-INFO
Products.SimpleReference.egg-info/SOURCES.txt
Products.SimpleReference.egg-info/dependency_links.txt
Products.SimpleReference.egg-info/entry_points.txt
Products.SimpleReference.egg-info/namespace_packages.txt
Products.SimpleReference.egg-info/not-zip-safe
Products.SimpleReference.egg-info/paster_plugins.txt
Products.SimpleReference.egg-info/requires.txt
Products.SimpleReference.egg-info/top_level.txt
Products/SimpleReference/__init__.py
Products/SimpleReference/_patches.py
Products/SimpleReference/config.py
Products/SimpleReference/configure.zcml
Products/SimpleReference/browser/__init__.py
Products/SimpleReference/browser/configure.zcml
Products/SimpleReference/browser/interfaces.py
Products/SimpleReference/browser/reference.py
Products/SimpleReference/browser/viewletmanager.py
Products/SimpleReference/browser/viewlets.py
Products/SimpleReference/browser/images/file_reference_icon.png
Products/SimpleReference/browser/images/image_reference_icon.png
Products/SimpleReference/browser/kss/widget_attachment.kss
Products/SimpleReference/browser/scripts/ecma.js
Products/SimpleReference/browser/templates/filelisting.pt
Products/SimpleReference/browser/templates/imagelisting.pt
Products/SimpleReference/browser/templates/reference_popup.pt
Products/SimpleReference/content/__init__.py
Products/SimpleReference/content/configure.zcml
Products/SimpleReference/content/file.py
Products/SimpleReference/content/file.txt
Products/SimpleReference/content/image.py
Products/SimpleReference/content/image.txt
Products/SimpleReference/interfaces/__init__.py
Products/SimpleReference/interfaces/simplereference.py
Products/SimpleReference/locales/de/LC_MESSAGES/README.txt
Products/SimpleReference/portlets/__init__.py
Products/SimpleReference/portlets/configure.zcml
Products/SimpleReference/profiles/default/Products.SimpleReference_various.txt
Products/SimpleReference/profiles/default/factorytool.xml
Products/SimpleReference/profiles/default/jsregistry.xml
Products/SimpleReference/profiles/default/kssregistry.xml
Products/SimpleReference/profiles/default/metadata.xml
Products/SimpleReference/profiles/default/portlets.xml
Products/SimpleReference/profiles/default/rolemap.xml
Products/SimpleReference/profiles/default/skins.xml
Products/SimpleReference/profiles/default/types.xml
