Metadata-Version: 1.0
Name: Products.SimpleReference
Version: 0.1b2
Summary: SimpleReference Content Type for RichDocument to enable Image/File referencing support
Home-page: http://svn.plone.org/svn/collective/
Author: UNKNOWN
Author-email: UNKNOWN
License: GPL
Platform: UNKNOWN
Classifier: Framework :: Plone
Classifier: Intended Audience :: Developers
Classifier: License :: OSI Approved :: GNU General Public License (GPL)
